[
    {
        "name": "Cooler",
        "videoRamCapacity": 17
    },
    {
        "name": "KingVegeta",
        "videoRamCapacity": 20
    },
    {
        "name": "Caulifla",
        "videoRamCapacity": 7
    },
    {
        "name": "SuperSaiyan2Gohan",
        "videoRamCapacity": 17
    },
    {
        "name": "Guru",
        "videoRamCapacity": 4
    },
    {
        "name": "KingKai",
        "videoRamCapacity": 6
    },
    {
        "name": "SuperSaiyan3Goku",
        "videoRamCapacity": 18
    },
    {
        "name": "RyuuShenlong",
        "videoRamCapacity": 5
    },
    {
        "name": "Tien",
        "videoRamCapacity": 19
    },
    {
        "name": "Bardock",
        "videoRamCapacity": 13
    },
    {
        "name": "SuShenlong",
        "videoRamCapacity": 20
    },
    {
        "name": "SuperSaiyanBlueVegeta",
        "videoRamCapacity": 12
    },
    {
        "name": "KidTrunks",
        "videoRamCapacity": 11
    },
    {
        "name": "MajinBuu",
        "videoRamCapacity": 11
    },
    {
        "name": "Yamcha",
        "videoRamCapacity": 3
    },
    {
        "name": "Android17",
        "videoRamCapacity": 20
    },
    {
        "name": "SanShenlong",
        "videoRamCapacity": 6
    },
    {
        "name": "SuperSaiyanVegeta",
        "videoRamCapacity": 14
    },
    {
        "name": "Launch",
        "videoRamCapacity": 4
    },
    {
        "name": "FutureTrunks",
        "videoRamCapacity": 16
    }
]